{
  "item.doorblade.hit_ground": {
    "sounds": [
      {
        "name": "item/trident/ground_impact1",
        "volume": 0.9
      },
      {
        "name": "item/trident/ground_impact2",
        "volume": 0.9
      },
      {
        "name": "item/trident/ground_impact3",
        "volume": 0.9
      },
      {
        "name": "item/trident/ground_impact4",
        "volume": 0.9
      }
    ],
    "subtitle": "subtitles.item.doorblade.hit_ground"
  },
  "item.doorlauncher.fire": {
    "sounds": [
      {
        "name": "item/armor/equip_netherite1",
        "volume": 0.8
      },
      {
        "name": "item/armor/equip_netherite1",
        "pitch": 0.9,
        "volume": 0.8
      },
      {
        "name": "item/armor/equip_netherite2",
        "volume": 0.8
      },
      {
        "name": "item/armor/equip_netherite2",
        "pitch": 0.9,
        "volume": 0.8
      },
      {
        "name": "item/armor/equip_netherite3",
        "volume": 0.8
      },
      {
        "name": "item/armor/equip_netherite3",
        "pitch": 0.9,
        "volume": 0.8
      },
      {
        "name": "item/armor/equip_netherite4",
        "volume": 0.8
      },
      {
        "name": "item/armor/equip_netherite4",
        "pitch": 0.9,
        "volume": 0.8
      }
    ],
    "subtitle": "subtitles.doorlauncher.fire"
  },
  "item.doorflipper.flip": {
    "sounds": [
      {
        "name": "halfdoors:doorflip",
        "volume": 0.8
      }
    ],
    "subtitle": "subtitles.doorflipper.flip"
  }
}